{
  "task": {
    "description": "Review and renew or renegotiate the contract with ACME Ltd.",
    "due_date": "2023-11-30",
    "priority": "High",
    "assigned_to": "Legal Team",
    "context": "Contract expires next month",
    "time_slot": "2025-05-29T09:00:00+02:00",
    "time_slot_source": "gpt",
    "time_slot_confidence": "medium",
    "assigned_user": {
      "name": "Legal Team"
    }
  },
  "result": {
    "task_id": "N/A",
    "target": "sheets",
    "status": "failed",
    "timestamp": "2025-05-29T06:26:00.249635"
  },
  "timestamp": "20250529_062603"
}